kompressor/__init__.py
kompressor/cli.py
kompressor/kompressor.py
kompressor/py.typed
kompressor-0.2.9.dist-info/METADATA
kompressor-0.2.9.dist-info/WHEEL
kompressor-0.2.9.dist-info/entry_points.txt
kompressor-0.2.9.dist-info/licenses/LICENSE
kompressor-0.2.9.dist-info/RECORD
