Metadata-Version: 2.4
Name: kompressor
Version: 0.2.9
Summary: Compress, resize, trim and convert images
Project-URL: Homepage, https://github.com/8cylinder/kompressor
Project-URL: Issues, https://github.com/8cylinder/kompressor/issues
Author-email: Sheldon McGrandle <developer@8cylinder.com>
License-File: LICENSE
Classifier: Intended Audience :: Developers
Classifier: License :: OSI Approved :: GNU General Public License v3 (GPLv3)
Classifier: Natural Language :: English
Classifier: Operating System :: MacOS
Classifier: Operating System :: POSIX :: Linux
Classifier: Programming Language :: Python :: 3.10
Classifier: Programming Language :: Python :: 3.11
Classifier: Programming Language :: Python :: 3.12
Classifier: Programming Language :: Python :: 3.13
Requires-Python: >=3.10
Requires-Dist: click>=8.1.7
Requires-Dist: pillow-avif-plugin>=1.5.2
Requires-Dist: pillow>=11.0.0
Requires-Dist: python-slugify>=8.0.4
